contu/contu.py
contu-0.3.dist-info/METADATA
contu-0.3.dist-info/WHEEL
contu-0.3.dist-info/top_level.txt
contu-0.3.dist-info/RECORD
