Metadata-Version: 2.1
Name: contu
Version: 0.3
Summary: A simple package that converts contracted forms of words to their uncontracted counterparts.
Home-page: https://github.com/Harshul-18/contu.git
Author: Harshul Nanda
Author-email: harshulnanda0@gmail.com
Classifier: Programming Language :: Python :: 3
Classifier: License :: OSI Approved :: MIT License
Classifier: Operating System :: OS Independent
Requires-Python: >=3.0
Requires-Dist: nltk
